{
  "_lookup": ["name"],
  "_translate": ["title"],
  "name": "i3val_contact_custom_updates",
  "title": "Contact Custom Fields Update",
  "extends": "Activity",
  "style": "Inline",
  "collapse_display": "1",
  "is_active": "1",
  "is_multiple": "1",
  "table_name": "civicrm_value_i3val_contact_custom_updates",
  "collapse_adv_display": "1",
  "is_reserved": "0",
  "_fields": [
    {
      "_lookup": ["column_name", "custom_group_id"],
      "_translate": ["label"],
      "name": "custom_field_id",
      "column_name": "custom_field_id",
      "label": "Custom Field ID",
      "data_type": "Integer",
      "html_type": "Text",
      "is_required": "0",
      "is_searchable": "1",
      "is_search_range": "1",
      "is_active": "1",
      "is_view": "1"
    },
    {
      "_lookup": ["column_name", "custom_group_id"],
      "_translate": ["label"],
      "name": "value_original",
      "column_name": "value_original",
      "label": "Value (original)",
      "data_type": "String",
      "html_type": "Text",
      "text_length": "255",
      "is_required": "0",
      "is_searchable": "1",
      "is_search_range": "1",
      "is_active": "1",
      "is_view": "1"
    },
    {
      "_lookup": ["column_name", "custom_group_id"],
      "_translate": ["label"],
      "name": "value_submitted",
      "column_name": "value_submitted",
      "label": "Value (submitted)",
      "data_type": "String",
      "html_type": "Text",
      "text_length": "255",
      "is_required": "0",
      "is_searchable": "1",
      "is_search_range": "1",
      "is_active": "1",
      "is_view": "1"
    },
    {
      "_lookup": ["column_name", "custom_group_id"],
      "_translate": ["label"],
      "name": "value_applied",
      "column_name": "value_applied",
      "label": "Value (applied)",
      "data_type": "String",
      "html_type": "Text",
      "text_length": "255",
      "is_required": "0",
      "is_searchable": "1",
      "is_search_range": "1",
      "is_active": "1",
      "is_view": "1"
    }
  ]
}